{
  "dashboard": {
    "id": null,
    "title": "CastMatch Production Overview",
    "tags": ["castmatch", "production", "overview"],
    "timezone": "UTC",
    "time": {
      "from": "now-1h",
      "to": "now"
    },
    "refresh": "30s",
    "schemaVersion": 36,
    "version": 0,
    "templating": {
      "list": [
        {
          "name": "environment",
          "type": "constant",
          "current": {
            "value": "production"
          },
          "hide": 2
        }
      ]
    },
    "panels": [
      {
        "id": 1,
        "title": "System Health Overview",
        "type": "stat",
        "gridPos": {
          "h": 8,
          "w": 24,
          "x": 0,
          "y": 0
        },
        "targets": [
          {
            "expr": "up{job=\"castmatch-api\"}",
            "legendFormat": "API Services"
          },
          {
            "expr": "up{job=\"postgresql\"}",
            "legendFormat": "Database"
          },
          {
            "expr": "up{job=\"redis\"}",
            "legendFormat": "Redis"
          },
          {
            "expr": "up{job=\"node-exporter\"}",
            "legendFormat": "Nodes"
          }
        ],
        "fieldConfig": {
          "defaults": {
            "color": {
              "mode": "thresholds"
            },
            "mappings": [
              {
                "options": {
                  "0": {
                    "text": "DOWN"
                  },
                  "1": {
                    "text": "UP"
                  }
                },
                "type": "value"
              }
            ],
            "thresholds": {
              "steps": [
                {
                  "color": "red",
                  "value": null
                },
                {
                  "color": "green",
                  "value": 1
                }
              ]
            }
          }
        },
        "options": {
          "colorMode": "background",
          "graphMode": "none",
          "justifyMode": "auto",
          "orientation": "auto",
          "reduceOptions": {
            "values": false,
            "calcs": ["lastNotNull"],
            "fields": ""
          },
          "textMode": "auto"
        }
      },
      {
        "id": 2,
        "title": "Request Rate (RPS)",
        "type": "graph",
        "gridPos": {
          "h": 8,
          "w": 12,
          "x": 0,
          "y": 8
        },
        "targets": [
          {
            "expr": "sum(rate(http_requests_total[5m]))",
            "legendFormat": "Total Requests/sec"
          },
          {
            "expr": "sum(rate(http_requests_total{status=~\"2..\"}[5m]))",
            "legendFormat": "2xx Responses/sec"
          },
          {
            "expr": "sum(rate(http_requests_total{status=~\"4..\"}[5m]))",
            "legendFormat": "4xx Responses/sec"
          },
          {
            "expr": "sum(rate(http_requests_total{status=~\"5..\"}[5m]))",
            "legendFormat": "5xx Responses/sec"
          }
        ],
        "yAxes": [
          {
            "label": "requests/sec",
            "min": 0
          }
        ],
        "legend": {
          "displayMode": "list",
          "placement": "bottom"
        }
      },
      {
        "id": 3,
        "title": "Response Time (95th percentile)",
        "type": "graph",
        "gridPos": {
          "h": 8,
          "w": 12,
          "x": 12,
          "y": 8
        },
        "targets": [
          {
            "expr": "histogram_quantile(0.95, sum(rate(http_request_duration_seconds_bucket[5m])) by (le))",
            "legendFormat": "95th percentile"
          },
          {
            "expr": "histogram_quantile(0.50, sum(rate(http_request_duration_seconds_bucket[5m])) by (le))",
            "legendFormat": "50th percentile"
          }
        ],
        "yAxes": [
          {
            "label": "seconds",
            "min": 0
          }
        ]
      },
      {
        "id": 4,
        "title": "Active Users",
        "type": "stat",
        "gridPos": {
          "h": 8,
          "w": 6,
          "x": 0,
          "y": 16
        },
        "targets": [
          {
            "expr": "sum(active_sessions_total)",
            "legendFormat": "Active Sessions"
          }
        ],
        "fieldConfig": {
          "defaults": {
            "color": {
              "mode": "palette-classic"
            },
            "unit": "short",
            "decimals": 0
          }
        }
      },
      {
        "id": 5,
        "title": "Database Connections",
        "type": "stat",
        "gridPos": {
          "h": 8,
          "w": 6,
          "x": 6,
          "y": 16
        },
        "targets": [
          {
            "expr": "sum(pgbouncer_pools_client_active)",
            "legendFormat": "Active Connections"
          }
        ],
        "fieldConfig": {
          "defaults": {
            "color": {
              "mode": "thresholds"
            },
            "thresholds": {
              "steps": [
                {
                  "color": "green",
                  "value": null
                },
                {
                  "color": "yellow",
                  "value": 80
                },
                {
                  "color": "red",
                  "value": 95
                }
              ]
            },
            "max": 100,
            "unit": "short"
          }
        }
      },
      {
        "id": 6,
        "title": "Error Rate",
        "type": "stat",
        "gridPos": {
          "h": 8,
          "w": 6,
          "x": 12,
          "y": 16
        },
        "targets": [
          {
            "expr": "sum(rate(http_requests_total{status=~\"5..\"}[5m])) / sum(rate(http_requests_total[5m])) * 100",
            "legendFormat": "5xx Error Rate %"
          }
        ],
        "fieldConfig": {
          "defaults": {
            "color": {
              "mode": "thresholds"
            },
            "thresholds": {
              "steps": [
                {
                  "color": "green",
                  "value": null
                },
                {
                  "color": "yellow",
                  "value": 1
                },
                {
                  "color": "red",
                  "value": 5
                }
              ]
            },
            "unit": "percent",
            "decimals": 2
          }
        }
      },
      {
        "id": 7,
        "title": "CPU Usage",
        "type": "stat",
        "gridPos": {
          "h": 8,
          "w": 6,
          "x": 18,
          "y": 16
        },
        "targets": [
          {
            "expr": "avg(100 - (avg by (instance) (irate(node_cpu_seconds_total{mode=\"idle\"}[5m])) * 100))",
            "legendFormat": "Average CPU %"
          }
        ],
        "fieldConfig": {
          "defaults": {
            "color": {
              "mode": "thresholds"
            },
            "thresholds": {
              "steps": [
                {
                  "color": "green",
                  "value": null
                },
                {
                  "color": "yellow",
                  "value": 70
                },
                {
                  "color": "red",
                  "value": 90
                }
              ]
            },
            "max": 100,
            "unit": "percent",
            "decimals": 1
          }
        }
      },
      {
        "id": 8,
        "title": "Database Performance",
        "type": "graph",
        "gridPos": {
          "h": 8,
          "w": 12,
          "x": 0,
          "y": 24
        },
        "targets": [
          {
            "expr": "rate(pg_stat_database_xact_commit[5m])",
            "legendFormat": "Commits/sec - {{ $labels.datname }}"
          },
          {
            "expr": "rate(pg_stat_database_xact_rollback[5m])",
            "legendFormat": "Rollbacks/sec - {{ $labels.datname }}"
          },
          {
            "expr": "rate(pg_stat_database_tup_inserted[5m])",
            "legendFormat": "Inserts/sec - {{ $labels.datname }}"
          },
          {
            "expr": "rate(pg_stat_database_tup_updated[5m])",
            "legendFormat": "Updates/sec - {{ $labels.datname }}"
          }
        ],
        "yAxes": [
          {
            "label": "operations/sec",
            "min": 0
          }
        ]
      },
      {
        "id": 9,
        "title": "Redis Performance",
        "type": "graph",
        "gridPos": {
          "h": 8,
          "w": 12,
          "x": 12,
          "y": 24
        },
        "targets": [
          {
            "expr": "rate(redis_commands_processed_total[5m])",
            "legendFormat": "Commands/sec"
          },
          {
            "expr": "redis_connected_clients",
            "legendFormat": "Connected Clients"
          },
          {
            "expr": "redis_memory_used_bytes",
            "legendFormat": "Memory Used"
          }
        ],
        "yAxes": [
          {
            "label": "ops/sec",
            "min": 0
          },
          {
            "label": "bytes",
            "min": 0,
            "side": "right"
          }
        ]
      },
      {
        "id": 10,
        "title": "Authentication Metrics",
        "type": "graph",
        "gridPos": {
          "h": 8,
          "w": 12,
          "x": 0,
          "y": 32
        },
        "targets": [
          {
            "expr": "rate(authentication_attempts_total[5m])",
            "legendFormat": "Auth Attempts/sec"
          },
          {
            "expr": "rate(authentication_successes_total[5m])",
            "legendFormat": "Auth Successes/sec"
          },
          {
            "expr": "rate(authentication_failures_total[5m])",
            "legendFormat": "Auth Failures/sec"
          },
          {
            "expr": "rate(password_resets_total[5m])",
            "legendFormat": "Password Resets/sec"
          }
        ],
        "yAxes": [
          {
            "label": "events/sec",
            "min": 0
          }
        ]
      },
      {
        "id": 11,
        "title": "Email Delivery Metrics",
        "type": "graph",
        "gridPos": {
          "h": 8,
          "w": 12,
          "x": 12,
          "y": 32
        },
        "targets": [
          {
            "expr": "rate(email_send_attempts_total[5m])",
            "legendFormat": "Send Attempts/sec"
          },
          {
            "expr": "rate(email_send_successes_total[5m])",
            "legendFormat": "Send Successes/sec"
          },
          {
            "expr": "rate(email_send_failures_total[5m])",
            "legendFormat": "Send Failures/sec"
          },
          {
            "expr": "rate(email_bounces_total[5m])",
            "legendFormat": "Bounces/sec"
          }
        ],
        "yAxes": [
          {
            "label": "emails/sec",
            "min": 0
          }
        ]
      },
      {
        "id": 12,
        "title": "Business Metrics",
        "type": "graph",
        "gridPos": {
          "h": 8,
          "w": 24,
          "x": 0,
          "y": 40
        },
        "targets": [
          {
            "expr": "increase(user_registrations_total[1h])",
            "legendFormat": "New Registrations (hourly)"
          },
          {
            "expr": "increase(castings_created_total[1h])",
            "legendFormat": "New Castings (hourly)"
          },
          {
            "expr": "increase(applications_submitted_total[1h])",
            "legendFormat": "Applications Submitted (hourly)"
          },
          {
            "expr": "increase(matches_made_total[1h])",
            "legendFormat": "Matches Made (hourly)"
          }
        ],
        "yAxes": [
          {
            "label": "count",
            "min": 0
          }
        ]
      },
      {
        "id": 13,
        "title": "Network Traffic",
        "type": "graph",
        "gridPos": {
          "h": 8,
          "w": 12,
          "x": 0,
          "y": 48
        },
        "targets": [
          {
            "expr": "rate(node_network_receive_bytes_total{device!=\"lo\"}[5m]) * 8",
            "legendFormat": "Inbound - {{ $labels.device }}"
          },
          {
            "expr": "rate(node_network_transmit_bytes_total{device!=\"lo\"}[5m]) * 8",
            "legendFormat": "Outbound - {{ $labels.device }}"
          }
        ],
        "yAxes": [
          {
            "label": "bits/sec",
            "min": 0
          }
        ]
      },
      {
        "id": 14,
        "title": "Disk I/O",
        "type": "graph",
        "gridPos": {
          "h": 8,
          "w": 12,
          "x": 12,
          "y": 48
        },
        "targets": [
          {
            "expr": "rate(node_disk_read_bytes_total[5m])",
            "legendFormat": "Read - {{ $labels.device }}"
          },
          {
            "expr": "rate(node_disk_written_bytes_total[5m])",
            "legendFormat": "Write - {{ $labels.device }}"
          }
        ],
        "yAxes": [
          {
            "label": "bytes/sec",
            "min": 0
          }
        ]
      }
    ]
  }
}